MANIFEST.in
README.rst
setup.py
educube/__init__.py
educube/client.py
educube.egg-info/PKG-INFO
educube.egg-info/SOURCES.txt
educube.egg-info/dependency_links.txt
educube.egg-info/entry_points.txt
educube.egg-info/not-zip-safe
educube.egg-info/requires.txt
educube.egg-info/top_level.txt
educube/commands/__init__.py
educube/commands/term.py
educube/lib/__init__.py
educube/lib/term.py
educube/util/__init__.py
educube/util/display.py
educube/util/educube_conn.py
educube/util/telemetry_parser.py
educube/web/__init__.py
educube/web/server.py
educube/web/ui_modules.py
educube/web/static/css/animate.css
educube/web/static/css/bootstrap.css
educube/web/static/css/bootstrap.min.css
educube/web/static/css/highcharts.css
educube/web/static/css/pnotify.custom.min.css
educube/web/static/css/portfolio-item.css
educube/web/static/css/sidebar.css
educube/web/static/fonts/glyphicons-halflings-regular.eot
educube/web/static/fonts/glyphicons-halflings-regular.svg
educube/web/static/fonts/glyphicons-halflings-regular.ttf
educube/web/static/fonts/glyphicons-halflings-regular.woff
educube/web/static/fonts/glyphicons-halflings-regular.woff2
educube/web/static/js/bootstrap.js
educube/web/static/js/bootstrap.min.js
educube/web/static/js/commands.js
educube/web/static/js/highcharts.js
educube/web/static/js/jquery.js
educube/web/static/js/jquery.tmpl.min.js
educube/web/static/js/pnotify.custom.min.js
educube/web/static/js/telemetry.js
educube/web/templates/base.html
educube/web/templates/educube.html
educube/web/templates/educube_adc.html
educube/web/templates/educube_cdh.html
educube/web/templates/educube_eps.html
educube/web/templates/educube_exp.html
educube/web/templates/educube_help.html
educube/web/templates/telemetry.html