Metadata-Version: 1.1
Name: educube
Version: 0.5.7
Summary: EduCube Client
Home-page: UNKNOWN
Author: UCD
Author-email: daniel.vagg@gmail.com
License: GPLv3
Download-URL: https://github.com/ezeakeal/educube_client/tarball/0.5.7
Keywords: educube
Platform: UNKNOWN
